arvados/__init__.py
arvados/_version.py
arvados/api.py
arvados/api_resources.py
arvados/arvfile.py
arvados/cache.py
arvados/collection.py
arvados/config.py
arvados/errors.py
arvados/events.py
arvados/keep.py
arvados/logging.py
arvados/retry.py
arvados/safeapi.py
arvados/util.py
arvados/vocabulary.py
arvados/_internal/__init__.py
arvados/_internal/basedirs.py
arvados/_internal/diskcache.py
arvados/_internal/downloaderbase.py
arvados/_internal/http_to_keep.py
arvados/_internal/pycurl.py
arvados/_internal/report_template.py
arvados/_internal/s3_to_keep.py
arvados/_internal/streams.py
arvados/_internal/to_keep_util.py
arvados/commands/__init__.py
arvados/commands/_util.py
arvados/commands/arv_copy.py
arvados/commands/get.py
arvados/commands/keepdocker.py
arvados/commands/ls.py
arvados/commands/put.py
arvados/commands/run.py
arvados/commands/ws.py
arvados_python_client-3.2.0.data/data/share/doc/arvados-python-client/LICENSE-2.0.txt
arvados_python_client-3.2.0.data/data/share/doc/arvados-python-client/README.rst
arvados_python_client-3.2.0.data/scripts/arv-copy
arvados_python_client-3.2.0.data/scripts/arv-get
arvados_python_client-3.2.0.data/scripts/arv-keepdocker
arvados_python_client-3.2.0.data/scripts/arv-ls
arvados_python_client-3.2.0.data/scripts/arv-normalize
arvados_python_client-3.2.0.data/scripts/arv-put
arvados_python_client-3.2.0.data/scripts/arv-ws
arvados_python_client-3.2.0.dist-info/licenses/LICENSE-2.0.txt
bin/arv-copy
bin/arv-get
bin/arv-keepdocker
bin/arv-ls
bin/arv-normalize
bin/arv-put
bin/arv-ws
arvados_python_client-3.2.0.dist-info/METADATA
arvados_python_client-3.2.0.dist-info/WHEEL
arvados_python_client-3.2.0.dist-info/top_level.txt
arvados_python_client-3.2.0.dist-info/RECORD
